{
    "data": [
        {
            "id": 1,
            "name": "Darren Eldder",
            "mentee_name": "Travis Trimble",
            "course": "Python",
            "since": "Wed May 20 2023",
            "time": "11.00 AM - 11.35 AM",
            "img": "assets/img/user/user1.jpg",
            "menImg": "assets/img/user/user6.jpg",
            "amount": "3700.00"
        },
        {
            "id": 2,
            "name": "Deborah Angel",
            "mentee_name": "Carl Kelly",
            "course": "Algebra",
            "since": "Wed Apr 10 2023",
            "time": "09.10 AM - 10.25 AM",
            "img": "assets/img/user/user2.jpg",
            "menImg": "assets/img/user/user7.jpg",
            "amount": "1700.00"
        },
        {
            "id": 3,
            "name": "Marvin Campbell",
            "mentee_name": "Gina Moore",
            "course": "Integrated Sum",
            "since": "Wed Sep 29 2023",
            "time": "01.00 AM - 10.35 PM",
            "img": "assets/img/user/user3.jpg",
            "menImg": "assets/img/user/user8.jpg",
            "amount": "1450.00"
        },
        {
            "id": 4,
            "name": "Ruby Perrin",
            "mentee_name": "Gina Moore",
            "course": "Java Script",
            "since": "Wed Dec 07 2023",
            "time": "06.40 AM - 09.35 PM",
            "img": "assets/img/user/user4.jpg",
            "menImg": "assets/img/user/user9.jpg",
            "amount": "1650.00"
        },
        {
            "id": 5,
            "name": "Sofia Brient",
            "mentee_name": "Michelle Fairfax",
            "course": "Flow chart",
            "since": "Wed Jul 06 2023",
            "time": "08.50 AM - 01.15 PM",
            "img": "assets/img/user/user5.jpg",
            "menImg": "assets/img/user/user10.jpg",
            "amount": "4230.00"
        },
        {
            "id": 6,
            "name": "Richard Wilson",
            "mentee_name": "Robert Rhodes",
            "course": "Basic Calculation",
            "since": "Wed Jun 18 2023",
            "time": "07.30 AM - 05.35 PM",
            "img": "assets/img/user/user11.jpg",
            "menImg": "assets/img/user/user16.jpg",
            "amount": "1487.00"
        },
        {
            "id": 7,
            "name": "Harry Williams",
            "mentee_name": "Joan Gardner",
            "course": "Algebra",
            "since": "Wed Nov 20 2023",
            "time": "11.00 AM - 11.35 AM",
            "img": "assets/img/user/user12.jpg",
            "menImg": "assets/img/user/user17.jpg",
            "amount": "3700.00"
        }
       
    ],
    "totalData": 7
}